eday/__init__.py
eday/__main__.py
eday/utils.py
eday-1.1.1.dist-info/LICENSE
eday-1.1.1.dist-info/METADATA
eday-1.1.1.dist-info/WHEEL
eday-1.1.1.dist-info/top_level.txt
eday-1.1.1.dist-info/RECORD
