Metadata-Version: 2.1
Name: eday
Version: 1.1.1
Summary: A package for converting between dates and epoch days
Home-page: https://github.com/mindey/eday
Author: Mindey
Author-email: mindey@mindey.com
License: MIT
Keywords: epoch days date time datetime conversion utility
Classifier: Development Status :: 5 - Production/Stable
Classifier: Intended Audience :: Developers
Classifier: Topic :: Software Development :: Libraries :: Python Modules
Classifier: License :: OSI Approved :: MIT License
Classifier: Programming Language :: Python :: 3
Classifier: Programming Language :: Python :: 3.5
Classifier: Programming Language :: Python :: 3.6
Classifier: Programming Language :: Python :: 3.7
Classifier: Programming Language :: Python :: 3.8
Classifier: Programming Language :: Python :: 3.9
Classifier: Programming Language :: Python :: 3.10
Classifier: Programming Language :: Python :: 3.11
Classifier: Programming Language :: Python :: 3.12
Requires-Python: >=3.5
License-File: LICENSE
Requires-Dist: juliandate
